{
  "query": "sum(waitingroom_entries_waiting)",
  "attemptedQueries": [
    "sum(waitingroom_entries_waiting)"
  ],
  "payload": {
    "status": "success",
    "data": {
      "resultType": "matrix",
      "result": [
        {
          "metric": {},
          "values": [
            [
              1782792529.367,
              "0"
            ],
            [
              1782792544.367,
              "5"
            ],
            [
              1782792559.367,
              "52"
            ],
            [
              1782792574.367,
              "80"
            ],
            [
              1782792589.367,
              "61"
            ],
            [
              1782792604.367,
              "74"
            ],
            [
              1782792619.367,
              "68"
            ],
            [
              1782792634.367,
              "51"
            ],
            [
              1782792649.367,
              "51"
            ],
            [
              1782792664.367,
              "68"
            ],
            [
              1782792679.367,
              "63"
            ],
            [
              1782792694.367,
              "65"
            ],
            [
              1782792709.367,
              "23"
            ]
          ]
        }
      ]
    }
  }
}