{
  "query": "sum(reservation_completed_total)",
  "attemptedQueries": [
    "sum(reservation_completed_total)"
  ],
  "payload": {
    "status": "success",
    "data": {
      "resultType": "matrix",
      "result": [
        {
          "metric": {},
          "values": [
            [
              1782791570.002,
              "62"
            ],
            [
              1782791585.002,
              "62"
            ],
            [
              1782791600.002,
              "62"
            ],
            [
              1782791615.002,
              "62"
            ],
            [
              1782791630.002,
              "62"
            ],
            [
              1782791645.002,
              "62"
            ],
            [
              1782791660.002,
              "62"
            ],
            [
              1782791675.002,
              "62"
            ],
            [
              1782791690.002,
              "62"
            ],
            [
              1782791705.002,
              "62"
            ],
            [
              1782791720.002,
              "62"
            ],
            [
              1782791735.002,
              "62"
            ]
          ]
        }
      ]
    }
  }
}