{
  "query": "sum(rate(http_server_requests_seconds_count[30s]))",
  "attemptedQueries": [
    "sum(rate(http_server_requests_seconds_count[30s]))"
  ],
  "payload": {
    "status": "success",
    "data": {
      "resultType": "matrix",
      "result": [
        {
          "metric": {},
          "values": [
            [
              1782790562.039,
              "3.5794864058911555"
            ],
            [
              1782790577.039,
              "72.38818188335185"
            ],
            [
              1782790592.039,
              "80.67844203680937"
            ],
            [
              1782790607.039,
              "79.86576033423644"
            ],
            [
              1782790622.039,
              "78.20836125260227"
            ],
            [
              1782790637.039,
              "77.06917400195607"
            ],
            [
              1782790652.039,
              "79.27982058869831"
            ],
            [
              1782790667.039,
              "79.93528038941122"
            ],
            [
              1782790682.039,
              "73.5237460367458"
            ],
            [
              1782790697.039,
              "73.42101822315497"
            ],
            [
              1782790712.039,
              "76.89564101046207"
            ],
            [
              1782790727.039,
              "74.7474657713579"
            ]
          ]
        }
      ]
    }
  }
}